agentui/__init__.py
agentui/cli.py
agentui/api/__init__.py
agentui/api/server.py
agentui/core/__init__.py
agentui/core/registry.py
agentui/core/tool.py
agentui/core/workflow.py
agentui/pixelflow/__init__.py
agentui/pixelflow/adjustments.py
agentui/pixelflow/filters.py
agentui/pixelflow/transforms.py
agentui/static/index.html
agentui/static/logo.png
agentui/static/assets/index-DJBuCFFW.js
agentui/static/assets/index-Du8AXONQ.css
agentui/tools/__init__.py
agentui/tools/base_tools.py
agentui/tools/cv_tools.py
agentui/tools/model_tools.py
agentui/tools/pixelflow_tools.py
agentui-0.1.1.dist-info/licenses/LICENSE
agentui-0.1.1.dist-info/METADATA
agentui-0.1.1.dist-info/WHEEL
agentui-0.1.1.dist-info/entry_points.txt
agentui-0.1.1.dist-info/top_level.txt
agentui-0.1.1.dist-info/RECORD
