Metadata-Version: 2.4
Name: agentui
Version: 0.1.1
Summary: Visual workflow builder for computer vision
Author-email: Emrah NAZIF <emrah@datamarkin.com>, Datamarkin <support@datamarkin.com>
License: MIT
Project-URL: Homepage, https://datamarkin.com
Project-URL: Repository, https://github.com/datamarkin/agentui
Project-URL: Documentation, https://github.com/datamarkin/agentui#readme
Project-URL: Issues, https://github.com/datamarkin/agentui/issues
Keywords: computer-vision,workflow,visual-programming,no-code,object-detection,image-processing,yolo,detectron2,segmentation,depth-estimation,annotation,tracking
Classifier: Development Status :: 3 - Alpha
Classifier: Intended Audience :: Developers
Classifier: Intended Audience :: Science/Research
Classifier: Intended Audience :: Education
Classifier: License :: OSI Approved :: MIT License
Classifier: Topic :: Scientific/Engineering :: Artificial Intelligence
Classifier: Topic :: Scientific/Engineering :: Image Recognition
Classifier: Topic :: Scientific/Engineering :: Image Processing
Classifier: Operating System :: OS Independent
Classifier: Programming Language :: Python :: 3
Classifier: Programming Language :: Python :: 3.9
Classifier: Programming Language :: Python :: 3.10
Classifier: Programming Language :: Python :: 3.11
Classifier: Programming Language :: Python :: 3.12
Requires-Python: >=3.9
License-File: LICENSE
Requires-Dist: tqdm>=4.64.0
Requires-Dist: pillow>=9.0.0
Requires-Dist: numpy>=1.21.0
Requires-Dist: fastapi>=0.100.0
Requires-Dist: uvicorn>=0.20.0
Requires-Dist: python-multipart>=0.0.6
Requires-Dist: pixelflow>=0.1.1
Requires-Dist: mozo>=0.2.0
Dynamic: license-file
